{
  "issues": [
    {
      "id": 8,
      "project": {
        "id": 1,
        "name": "Test Project"
      },
      "tracker": {
        "id": 1,
        "name": "Bug"
      },
      "status": {
        "id": 1,
        "name": "New",
        "is_closed": false
      },
      "priority": {
        "id": 4,
        "name": "High"
      },
      "author": {
        "id": 1,
        "name": "Redmine Admin"
      },
      "assigned_to": {
        "id": 1,
        "name": "Redmine Admin"
      },
      "fixed_version": {
        "id": 2,
        "name": "v2"
      },
      "subject": "Test flow data redmine",
      "description": "Test flow data redmine of description",
      "start_date": "2026-01-16",
      "due_date": "2026-01-31",
      "done_ratio": 80,
      "is_private": false,
      "estimated_hours": 88,
      "total_estimated_hours": 88,
      "custom_fields": [
        {
          "id": 3,
          "name": "Test Boolean",
          "value": "1"
        },
        {
          "id": 6,
          "name": "Test Date",
          "value": "2026-01-13"
        },
        {
          "id": 7,
          "name": "Test File",
          "value": "14"
        },
        {
          "id": 8,
          "name": "Test Float",
          "value": "8.8"
        },
        {
          "id": 9,
          "name": "Test Integer",
          "value": "88"
        },
        {
          "id": 10,
          "name": "Test Key/Value List",
          "value": "1"
        },
        {
          "id": 12,
          "name": "Test Link",
          "value": "www.example88.com"
        },
        {
          "id": 13,
          "name": "Test List",
          "value": "Option 2"
        },
        {
          "id": 15,
          "name": "Test Long Text",
          "value": "Test flow data redmine of long text"
        },
        {
          "id": 16,
          "name": "Test Progress Bar",
          "value": "80"
        },
        {
          "id": 17,
          "name": "Test Text",
          "value": "Test flow data redmine of text"
        },
        {
          "id": 18,
          "name": "Test User",
          "value": ""
        },
        {
          "id": 20,
          "name": "Test Version",
          "value": "2"
        }
      ],
      "created_on": "2026-01-16T02:44:44Z",
      "updated_on": "2026-01-16T02:44:44Z",
      "closed_on": null
    }
  ],
  "total_count": 1,
  "offset": 0,
  "limit": 25
}